README.md
setup.py
vmtools/__init__.py
vmtools/vmtools.py
vmtools.egg-info/PKG-INFO
vmtools.egg-info/SOURCES.txt
vmtools.egg-info/dependency_links.txt
vmtools.egg-info/not-zip-safe
vmtools.egg-info/top_level.txt