Metadata-Version: 2.1
Name: vmtools
Version: 0.45
Summary: misc tools to make working with python virtualenv easier
Home-page: https://github.com/ranamalo/vmtools.git
Author: Banio Carpenter
Author-email: banio@mncarpenters.net
License: BSD
Platform: UNKNOWN
Classifier: Development Status :: 3 - Alpha
Classifier: Environment :: Web Environment
Classifier: Intended Audience :: Developers
Classifier: License :: OSI Approved :: BSD License
Classifier: Operating System :: OS Independent
Classifier: Programming Language :: Python :: 3.5
